Workbook

Sheet Summary
A1: Portside Digital: Money Summary
A2: Everything here is calculated from the Income, Expenses and Settings tabs.
A4: Totals
A5: Total earned (paid) | B5: =SUMIFS(Income!D:D,Income!E:E,"Paid")
A6: Still owed by clients | B6: =SUMIFS(Income!D:D,Income!E:E,"Owed")
A7: Business spending | B7: =SUM(Expenses!D:D)
A8: Where the money goes
A9: Tax & NIS set aside | B9: =SUM(Income!H:H)
A10: Business costs money | B10: =SUM(Income!I:I)
A11: Business money left after spending | B11: =B10-B7
A12: Emergency fund | B12: =SUM(Income!J:J)
A13: Pay yourself | B13: =SUM(Income!K:K)
A14: Goals
A15: Months of Claude Max covered | B15: =IF(Settings!B14=0,0,B11/Settings!B14)
A16: Emergency fund progress | B16: =IF(N(Settings!B12)=0,0,B12/Settings!B12)
A17: Left to save for the PC | B17: =MAX(0,N(Settings!B13)-Settings!B16)
A18: PC savings progress | B18: =IF(N(Settings!B13)=0,0,Settings!B16/Settings!B13)
A21: By month
A22: Month | B22: Earned (paid) | C22: Still owed | D22: Business spending | E22: Tax & NIS set aside | F22: Pay yourself
A23: 46296 | B23: =SUMIFS(Income!$D:$D,Income!$L:$L,$A23,Income!$E:$E,"Paid") | C23: =SUMIFS(Income!$D:$D,Income!$L:$L,$A23,Income!$E:$E,"Owed") | D23: =SUMIFS(Expenses!$D:$D,Expenses!$G:$G,$A23) | E23: =SUMIFS(Income!$H:$H,Income!$L:$L,$A23) | F23: =SUMIFS(Income!$K:$K,Income!$L:$L,$A23)
A24: =EDATE(A23,1) | B24: =SUMIFS(Income!$D:$D,Income!$L:$L,$A24,Income!$E:$E,"Paid") | C24: =SUMIFS(Income!$D:$D,Income!$L:$L,$A24,Income!$E:$E,"Owed") | D24: =SUMIFS(Expenses!$D:$D,Expenses!$G:$G,$A24) | E24: =SUMIFS(Income!$H:$H,Income!$L:$L,$A24) | F24: =SUMIFS(Income!$K:$K,Income!$L:$L,$A24)
A25: =EDATE(A24,1) | B25: =SUMIFS(Income!$D:$D,Income!$L:$L,$A25,Income!$E:$E,"Paid") | C25: =SUMIFS(Income!$D:$D,Income!$L:$L,$A25,Income!$E:$E,"Owed") | D25: =SUMIFS(Expenses!$D:$D,Expenses!$G:$G,$A25) | E25: =SUMIFS(Income!$H:$H,Income!$L:$L,$A25) | F25: =SUMIFS(Income!$K:$K,Income!$L:$L,$A25)
A26: =EDATE(A25,1) | B26: =SUMIFS(Income!$D:$D,Income!$L:$L,$A26,Income!$E:$E,"Paid") | C26: =SUMIFS(Income!$D:$D,Income!$L:$L,$A26,Income!$E:$E,"Owed") | D26: =SUMIFS(Expenses!$D:$D,Expenses!$G:$G,$A26) | E26: =SUMIFS(Income!$H:$H,Income!$L:$L,$A26) | F26: =SUMIFS(Income!$K:$K,Income!$L:$L,$A26)
A27: =EDATE(A26,1) | B27: =SUMIFS(Income!$D:$D,Income!$L:$L,$A27,Income!$E:$E,"Paid") | C27: =SUMIFS(Income!$D:$D,Income!$L:$L,$A27,Income!$E:$E,"Owed") | D27: =SUMIFS(Expenses!$D:$D,Expenses!$G:$G,$A27) | E27: =SUMIFS(Income!$H:$H,Income!$L:$L,$A27) | F27: =SUMIFS(Income!$K:$K,Income!$L:$L,$A27)
A28: =EDATE(A27,1) | B28: =SUMIFS(Income!$D:$D,Income!$L:$L,$A28,Income!$E:$E,"Paid") | C28: =SUMIFS(Income!$D:$D,Income!$L:$L,$A28,Income!$E:$E,"Owed") | D28: =SUMIFS(Expenses!$D:$D,Expenses!$G:$G,$A28) | E28: =SUMIFS(Income!$H:$H,Income!$L:$L,$A28) | F28: =SUMIFS(Income!$K:$K,Income!$L:$L,$A28)
A29: =EDATE(A28,1) | B29: =SUMIFS(Income!$D:$D,Income!$L:$L,$A29,Income!$E:$E,"Paid") | C29: =SUMIFS(Income!$D:$D,Income!$L:$L,$A29,Income!$E:$E,"Owed") | D29: =SUMIFS(Expenses!$D:$D,Expenses!$G:$G,$A29) | E29: =SUMIFS(Income!$H:$H,Income!$L:$L,$A29) | F29: =SUMIFS(Income!$K:$K,Income!$L:$L,$A29)
A30: =EDATE(A29,1) | B30: =SUMIFS(Income!$D:$D,Income!$L:$L,$A30,Income!$E:$E,"Paid") | C30: =SUMIFS(Income!$D:$D,Income!$L:$L,$A30,Income!$E:$E,"Owed") | D30: =SUMIFS(Expenses!$D:$D,Expenses!$G:$G,$A30) | E30: =SUMIFS(Income!$H:$H,Income!$L:$L,$A30) | F30: =SUMIFS(Income!$K:$K,Income!$L:$L,$A30)
A31: =EDATE(A30,1) | B31: =SUMIFS(Income!$D:$D,Income!$L:$L,$A31,Income!$E:$E,"Paid") | C31: =SUMIFS(Income!$D:$D,Income!$L:$L,$A31,Income!$E:$E,"Owed") | D31: =SUMIFS(Expenses!$D:$D,Expenses!$G:$G,$A31) | E31: =SUMIFS(Income!$H:$H,Income!$L:$L,$A31) | F31: =SUMIFS(Income!$K:$K,Income!$L:$L,$A31)
A32: =EDATE(A31,1) | B32: =SUMIFS(Income!$D:$D,Income!$L:$L,$A32,Income!$E:$E,"Paid") | C32: =SUMIFS(Income!$D:$D,Income!$L:$L,$A32,Income!$E:$E,"Owed") | D32: =SUMIFS(Expenses!$D:$D,Expenses!$G:$G,$A32) | E32: =SUMIFS(Income!$H:$H,Income!$L:$L,$A32) | F32: =SUMIFS(Income!$K:$K,Income!$L:$L,$A32)
A33: =EDATE(A32,1) | B33: =SUMIFS(Income!$D:$D,Income!$L:$L,$A33,Income!$E:$E,"Paid") | C33: =SUMIFS(Income!$D:$D,Income!$L:$L,$A33,Income!$E:$E,"Owed") | D33: =SUMIFS(Expenses!$D:$D,Expenses!$G:$G,$A33) | E33: =SUMIFS(Income!$H:$H,Income!$L:$L,$A33) | F33: =SUMIFS(Income!$K:$K,Income!$L:$L,$A33)
A34: =EDATE(A33,1) | B34: =SUMIFS(Income!$D:$D,Income!$L:$L,$A34,Income!$E:$E,"Paid") | C34: =SUMIFS(Income!$D:$D,Income!$L:$L,$A34,Income!$E:$E,"Owed") | D34: =SUMIFS(Expenses!$D:$D,Expenses!$G:$G,$A34) | E34: =SUMIFS(Income!$H:$H,Income!$L:$L,$A34) | F34: =SUMIFS(Income!$K:$K,Income!$L:$L,$A34)
A35: Total | B35: =SUM(B23:B34) | C35: =SUM(C23:C34) | D35: =SUM(D23:D34) | E35: =SUM(E23:E34) | F35: =SUM(F23:F34)

Sheet Settings
A1: Settings
A2: Blue text = numbers you can change. Yellow = fill in. Black = formulas, don't type over them.
A4: How each payment is split
A5: Tax & NIS savings | B5: 0.2
A6: Business costs | B6: 0.15
A7: Emergency fund | B7: 0.15
A8: Pay yourself | B8: =1-SUM(B5:B7)
A9: Total (must be 100%) | B9: =SUM(B5:B8)
A11: Goals
A12: Emergency fund target | C12: About 3 months of your bills
A13: PC build budget | C13: Your total quote for the PC
A14: Claude Max cost per month | B14: 680 | C14: About US$100 a month; check the current price and exchange rate
A16: Saved toward PC so far | B16: 0 | C16: Update this when you move money into PC savings

Sheet Income
A1: Date | B1: Client | C1: What for | D1: Amount (TT$) | E1: Status | F1: Payment method | G1: Notes | H1: Tax & NIS | I1: Business costs | J1: Emergency fund | K1: Pay yourself | L1: Month
A2: 46308 | B2: Example Boutique | C2: Website deposit (50%) | D2: 8000 | E2: Paid | F2: Bank transfer | G2: Example row: replace or delete | H2: =IF($E2="Paid",$D2*Settings!$B$5,"") | I2: =IF($E2="Paid",$D2*Settings!$B$6,"") | J2: =IF($E2="Paid",$D2*Settings!$B$7,"") | K2: =IF($E2="Paid",$D2*Settings!$B$8,"") | L2: =IF($A2="","",DATE(YEAR($A2),MONTH($A2),1))
H3: =IF($E3="Paid",$D3*Settings!$B$5,"") | I3: =IF($E3="Paid",$D3*Settings!$B$6,"") | J3: =IF($E3="Paid",$D3*Settings!$B$7,"") | K3: =IF($E3="Paid",$D3*Settings!$B$8,"") | L3: =IF($A3="","",DATE(YEAR($A3),MONTH($A3),1))
H4: =IF($E4="Paid",$D4*Settings!$B$5,"") | I4: =IF($E4="Paid",$D4*Settings!$B$6,"") | J4: =IF($E4="Paid",$D4*Settings!$B$7,"") | K4: =IF($E4="Paid",$D4*Settings!$B$8,"") | L4: =IF($A4="","",DATE(YEAR($A4),MONTH($A4),1))
H5: =IF($E5="Paid",$D5*Settings!$B$5,"") | I5: =IF($E5="Paid",$D5*Settings!$B$6,"") | J5: =IF($E5="Paid",$D5*Settings!$B$7,"") | K5: =IF($E5="Paid",$D5*Settings!$B$8,"") | L5: =IF($A5="","",DATE(YEAR($A5),MONTH($A5),1))
H6: =IF($E6="Paid",$D6*Settings!$B$5,"") | I6: =IF($E6="Paid",$D6*Settings!$B$6,"") | J6: =IF($E6="Paid",$D6*Settings!$B$7,"") | K6: =IF($E6="Paid",$D6*Settings!$B$8,"") | L6: =IF($A6="","",DATE(YEAR($A6),MONTH($A6),1))
H7: =IF($E7="Paid",$D7*Settings!$B$5,"") | I7: =IF($E7="Paid",$D7*Settings!$B$6,"") | J7: =IF($E7="Paid",$D7*Settings!$B$7,"") | K7: =IF($E7="Paid",$D7*Settings!$B$8,"") | L7: =IF($A7="","",DATE(YEAR($A7),MONTH($A7),1))
H8: =IF($E8="Paid",$D8*Settings!$B$5,"") | I8: =IF($E8="Paid",$D8*Settings!$B$6,"") | J8: =IF($E8="Paid",$D8*Settings!$B$7,"") | K8: =IF($E8="Paid",$D8*Settings!$B$8,"") | L8: =IF($A8="","",DATE(YEAR($A8),MONTH($A8),1))
H9: =IF($E9="Paid",$D9*Settings!$B$5,"") | I9: =IF($E9="Paid",$D9*Settings!$B$6,"") | J9: =IF($E9="Paid",$D9*Settings!$B$7,"") | K9: =IF($E9="Paid",$D9*Settings!$B$8,"") | L9: =IF($A9="","",DATE(YEAR($A9),MONTH($A9),1))
H10: =IF($E10="Paid",$D10*Settings!$B$5,"") | I10: =IF($E10="Paid",$D10*Settings!$B$6,"") | J10: =IF($E10="Paid",$D10*Settings!$B$7,"") | K10: =IF($E10="Paid",$D10*Settings!$B$8,"") | L10: =IF($A10="","",DATE(YEAR($A10),MONTH($A10),1))
H11: =IF($E11="Paid",$D11*Settings!$B$5,"") | I11: =IF($E11="Paid",$D11*Settings!$B$6,"") | J11: =IF($E11="Paid",$D11*Settings!$B$7,"") | K11: =IF($E11="Paid",$D11*Settings!$B$8,"") | L11: =IF($A11="","",DATE(YEAR($A11),MONTH($A11),1))
H12: =IF($E12="Paid",$D12*Settings!$B$5,"") | I12: =IF($E12="Paid",$D12*Settings!$B$6,"") | J12: =IF($E12="Paid",$D12*Settings!$B$7,"") | K12: =IF($E12="Paid",$D12*Settings!$B$8,"") | L12: =IF($A12="","",DATE(YEAR($A12),MONTH($A12),1))
H13: =IF($E13="Paid",$D13*Settings!$B$5,"") | I13: =IF($E13="Paid",$D13*Settings!$B$6,"") | J13: =IF($E13="Paid",$D13*Settings!$B$7,"") | K13: =IF($E13="Paid",$D13*Settings!$B$8,"") | L13: =IF($A13="","",DATE(YEAR($A13),MONTH($A13),1))
H14: =IF($E14="Paid",$D14*Settings!$B$5,"") | I14: =IF($E14="Paid",$D14*Settings!$B$6,"") | J14: =IF($E14="Paid",$D14*Settings!$B$7,"") | K14: =IF($E14="Paid",$D14*Settings!$B$8,"") | L14: =IF($A14="","",DATE(YEAR($A14),MONTH($A14),1))
... H151: =IF($E151="Paid",$D151*Settings!$B$5,"") | I151: =IF($E151="Paid",$D151*Settings!$B$6,"") | J151: =IF($E151="Paid",$D151*Settings!$B$7,"") | K151: =IF($E151="Paid",$D151*Settings!$B$8,"") | L151: =IF($A151="","",DATE(YEAR($A151),MONTH($A151),1))

Sheet Expenses
A1: Date | B1: What | C1: Category | D1: Amount (TT$) | E1: Receipt saved? | F1: Notes | G1: Month
A2: 46308 | B2: Claude Pro plan | C2: Claude | D2: 140 | E2: Yes | F2: Example row: replace or delete | G2: =IF($A2="","",DATE(YEAR($A2),MONTH($A2),1))
G3: =IF($A3="","",DATE(YEAR($A3),MONTH($A3),1))
G4: =IF($A4="","",DATE(YEAR($A4),MONTH($A4),1))
G5: =IF($A5="","",DATE(YEAR($A5),MONTH($A5),1))
G6: =IF($A6="","",DATE(YEAR($A6),MONTH($A6),1))
G7: =IF($A7="","",DATE(YEAR($A7),MONTH($A7),1))
G8: =IF($A8="","",DATE(YEAR($A8),MONTH($A8),1))
G9: =IF($A9="","",DATE(YEAR($A9),MONTH($A9),1))
G10: =IF($A10="","",DATE(YEAR($A10),MONTH($A10),1))
G11: =IF($A11="","",DATE(YEAR($A11),MONTH($A11),1))
G12: =IF($A12="","",DATE(YEAR($A12),MONTH($A12),1))
G13: =IF($A13="","",DATE(YEAR($A13),MONTH($A13),1))
G14: =IF($A14="","",DATE(YEAR($A14),MONTH($A14),1))
... G151: =IF($A151="","",DATE(YEAR($A151),MONTH($A151),1))
